{
    "graph": [], 
    "adjacency": [
        [
            {
                "languages": 9.0, 
                "weight": 4.0, 
                "id": "horn, trumpet", 
                "families": 4.0
            }, 
            {
                "languages": 2.0, 
                "weight": 2.0, 
                "id": "pipe", 
                "families": 2.0
            }
        ], 
        [
            {
                "languages": 18.0, 
                "weight": 7.0, 
                "id": "horn, trumpet", 
                "families": 7.0
            }
        ], 
        [
            {
                "languages": 12.0, 
                "weight": 9.0, 
                "id": "horn, trumpet", 
                "families": 9.0
            }
        ], 
        [
            {
                "languages": 9.0, 
                "weight": 4.0, 
                "id": "chimney", 
                "families": 4.0
            }, 
            {
                "languages": 18.0, 
                "weight": 7.0, 
                "id": "horn", 
                "families": 7.0
            }, 
            {
                "languages": 12.0, 
                "weight": 9.0, 
                "id": "flute", 
                "families": 9.0
            }, 
            {
                "languages": 4.0, 
                "weight": 2.0, 
                "id": "pipe", 
                "families": 2.0
            }
        ], 
        [
            {
                "languages": 2.0, 
                "weight": 2.0, 
                "id": "chimney", 
                "families": 2.0
            }, 
            {
                "languages": 4.0, 
                "weight": 2.0, 
                "id": "horn, trumpet", 
                "families": 2.0
            }
        ]
    ], 
    "nodes": [
        {
            "swadesh100": 0, 
            "key": "7.33", 
            "body_part": 0, 
            "community": 102, 
            "id": "chimney"
        }, 
        {
            "swadesh100": 1, 
            "key": "4.17", 
            "body_part": 1, 
            "community": 102, 
            "id": "horn"
        }, 
        {
            "swadesh100": 0, 
            "key": "18.71", 
            "body_part": 0, 
            "community": 102, 
            "id": "flute"
        }, 
        {
            "swadesh100": 0, 
            "key": "18.73", 
            "body_part": 0, 
            "community": 102, 
            "id": "horn, trumpet"
        }, 
        {
            "swadesh100": 0, 
            "key": "8.691", 
            "body_part": 0, 
            "community": 102, 
            "id": "pipe"
        }
    ], 
    "multigraph": false, 
    "directed": false
}