{"multigraph": false, "graph": [], "directed": false, "adjacency": [[{"id": "fingernail", "families": 35.0, "weight": 1441.1764705882354, "languages": 90.0, "edge_width": 13.484693877551019}], [{"id": "claw", "families": 35.0, "weight": 1441.1764705882354, "languages": 90.0, "edge_width": 13.484693877551019}]], "nodes": [{"id": "claw", "community": 108, "body_part": 1, "key": "4.345", "swadesh100": 1, "out_edge": [["cluster_203_toe", "finger", 6.0, 31.57894736842105, "fingernail"], ["cluster_203_toe", "toe", 5.0, 22.321428571428573, "fingernail"]]}, {"id": "fingernail", "community": 108, "body_part": 1, "key": "4.344", "swadesh100": 0, "out_edge": []}]}