{
    "directed": false, 
    "adjacency": [
        [
            {
                "weight": 3.508771929824561, 
                "normalized_weight": 3.508771929824561, 
                "languages": 2.0, 
                "families": 2.0, 
                "edge_width": 0.5, 
                "id": "palm of hand"
            }, 
            {
                "weight": 31.57894736842105, 
                "normalized_weight": 31.57894736842105, 
                "languages": 6.0, 
                "families": 6.0, 
                "edge_width": 0.79081632653061229, 
                "id": "hand"
            }, 
            {
                "weight": 13.91304347826087, 
                "normalized_weight": 13.91304347826087, 
                "languages": 4.0, 
                "families": 4.0, 
                "edge_width": 0.59693877551020402, 
                "id": "arm"
            }
        ], 
        [
            {
                "weight": 31.57894736842105, 
                "normalized_weight": 31.57894736842105, 
                "languages": 6.0, 
                "families": 6.0, 
                "edge_width": 0.79081632653061229, 
                "id": "wrist"
            }, 
            {
                "weight": 0.7874015748031495, 
                "normalized_weight": 0.7874015748031495, 
                "languages": 1.0, 
                "families": 1.0, 
                "edge_width": 0.5, 
                "id": "hand"
            }, 
            {
                "weight": 508.6538461538462, 
                "normalized_weight": 508.6538461538462, 
                "languages": 74.0, 
                "families": 23.0, 
                "edge_width": 5.25, 
                "id": "arm"
            }, 
            {
                "weight": 13.333333333333334, 
                "normalized_weight": 13.333333333333334, 
                "languages": 4.0, 
                "families": 4.0, 
                "edge_width": 0.59693877551020402, 
                "id": "branch"
            }, 
            {
                "weight": 1.0526315789473684, 
                "normalized_weight": 1.0526315789473684, 
                "languages": 1.0, 
                "families": 1.0, 
                "edge_width": 0.5, 
                "id": "span, fathom"
            }, 
            {
                "weight": 4.081632653061225, 
                "normalized_weight": 4.081632653061225, 
                "languages": 2.0, 
                "families": 2.0, 
                "edge_width": 0.5, 
                "id": "glove"
            }, 
            {
                "weight": 21.008403361344538, 
                "normalized_weight": 21.008403361344538, 
                "languages": 5.0, 
                "families": 5.0, 
                "edge_width": 0.69387755102040816, 
                "id": "palm of hand"
            }
        ], 
        [
            {
                "weight": 13.91304347826087, 
                "normalized_weight": 13.91304347826087, 
                "languages": 4.0, 
                "families": 4.0, 
                "edge_width": 0.59693877551020402, 
                "id": "wrist"
            }, 
            {
                "weight": 508.6538461538462, 
                "normalized_weight": 508.6538461538462, 
                "languages": 74.0, 
                "families": 23.0, 
                "edge_width": 5.25, 
                "id": "hand"
            }, 
            {
                "weight": 42.241379310344826, 
                "normalized_weight": 42.241379310344826, 
                "languages": 9.0, 
                "families": 7.0, 
                "edge_width": 0.88775510204081631, 
                "id": "branch"
            }, 
            {
                "weight": 9.782608695652174, 
                "normalized_weight": 9.782608695652174, 
                "languages": 3.0, 
                "families": 3.0, 
                "edge_width": 0.59693877551020402, 
                "id": "span, fathom"
            }, 
            {
                "weight": 0.819672131147541, 
                "normalized_weight": 0.819672131147541, 
                "languages": 1.0, 
                "families": 1.0, 
                "edge_width": 0.5, 
                "id": "palm of hand"
            }, 
            {
                "weight": 3.508771929824561, 
                "normalized_weight": 3.508771929824561, 
                "languages": 2.0, 
                "families": 2.0, 
                "edge_width": 0.5, 
                "id": "forked branch"
            }
        ], 
        [
            {
                "weight": 77.88461538461539, 
                "normalized_weight": 77.88461538461539, 
                "languages": 20.0, 
                "families": 9.0, 
                "edge_width": 1.1785714285714286, 
                "id": "forked branch"
            }, 
            {
                "weight": 42.241379310344826, 
                "normalized_weight": 42.241379310344826, 
                "languages": 9.0, 
                "families": 7.0, 
                "edge_width": 0.88775510204081631, 
                "id": "arm"
            }, 
            {
                "weight": 13.333333333333334, 
                "normalized_weight": 13.333333333333334, 
                "languages": 4.0, 
                "families": 4.0, 
                "edge_width": 0.59693877551020402, 
                "id": "hand"
            }
        ], 
        [
            {
                "weight": 9.782608695652174, 
                "normalized_weight": 9.782608695652174, 
                "languages": 3.0, 
                "families": 3.0, 
                "edge_width": 0.59693877551020402, 
                "id": "arm"
            }, 
            {
                "weight": 1.0526315789473684, 
                "normalized_weight": 1.0526315789473684, 
                "languages": 1.0, 
                "families": 1.0, 
                "edge_width": 0.5, 
                "id": "hand"
            }
        ], 
        [
            {
                "weight": 4.081632653061225, 
                "normalized_weight": 4.081632653061225, 
                "languages": 2.0, 
                "families": 2.0, 
                "edge_width": 0.5, 
                "id": "hand"
            }
        ], 
        [
            {
                "weight": 3.508771929824561, 
                "normalized_weight": 3.508771929824561, 
                "languages": 2.0, 
                "families": 2.0, 
                "edge_width": 0.5, 
                "id": "wrist"
            }, 
            {
                "weight": 0.819672131147541, 
                "normalized_weight": 0.819672131147541, 
                "languages": 1.0, 
                "families": 1.0, 
                "edge_width": 0.5, 
                "id": "arm"
            }, 
            {
                "weight": 21.008403361344538, 
                "normalized_weight": 21.008403361344538, 
                "languages": 5.0, 
                "families": 5.0, 
                "edge_width": 0.69387755102040816, 
                "id": "hand"
            }
        ], 
        [
            {
                "weight": 3.508771929824561, 
                "normalized_weight": 3.508771929824561, 
                "languages": 2.0, 
                "families": 2.0, 
                "edge_width": 0.5, 
                "id": "arm"
            }, 
            {
                "weight": 77.88461538461539, 
                "normalized_weight": 77.88461538461539, 
                "languages": 20.0, 
                "families": 9.0, 
                "edge_width": 1.1785714285714286, 
                "id": "branch"
            }
        ]
    ], 
    "multigraph": false, 
    "nodes": [
        {
            "key": "4.321", 
            "languages": 2.0, 
            "out_edge": [], 
            "weight": 2.0, 
            "community": 38, 
            "normalized_weight": 3.508771929824561, 
            "families": 2.0, 
            "id": "wrist"
        }, 
        {
            "key": "4.33", 
            "swadesh100": 1.0, 
            "frequency": 250.0, 
            "languages": 5.0, 
            "out_edge": [
                [
                    "cluster_204_toe", 
                    "finger", 
                    6.0, 
                    29.75206611570248
                ]
            ], 
            "label": "hand", 
            "concept": "hand", 
            "weight": 5.0, 
            "body_part": 1.0, 
            "community": 38, 
            "normalized_weight": 21.008403361344538, 
            "families": 5.0, 
            "id": "hand"
        }, 
        {
            "key": "4.31", 
            "swadesh100": 0.0, 
            "frequency": 260.0, 
            "languages": 1.0, 
            "out_edge": [
                [
                    "cluster_1_fur", 
                    "wing", 
                    6.0, 
                    30.0
                ], 
                [
                    "cluster_157_shoulder", 
                    "shoulder", 
                    4.0, 
                    13.114754098360656
                ]
            ], 
            "label": "arm", 
            "concept": "arm", 
            "weight": 1.0, 
            "body_part": 1.0, 
            "community": 38, 
            "normalized_weight": 0.819672131147541, 
            "families": 1.0, 
            "id": "arm"
        }, 
        {
            "key": "8.55", 
            "swadesh100": 0.0, 
            "frequency": 275.0, 
            "languages": 5.0, 
            "out_edge": [], 
            "label": "branch", 
            "concept": "branch", 
            "weight": 3.0, 
            "body_part": 0.0, 
            "community": 38, 
            "normalized_weight": 7.758620689655173, 
            "families": 3.0, 
            "id": "branch"
        }, 
        {
            "key": "12.541", 
            "swadesh100": 0.0, 
            "frequency": 161.0, 
            "languages": 1.0, 
            "out_edge": [], 
            "label": "span, fathom", 
            "concept": "span, fathom", 
            "weight": 1.0, 
            "body_part": 0.0, 
            "community": 38, 
            "normalized_weight": 1.0752688172043012, 
            "families": 1.0, 
            "id": "span, fathom"
        }, 
        {
            "key": "6.58", 
            "languages": 1.0, 
            "out_edge": [], 
            "weight": 1.0, 
            "community": 38, 
            "normalized_weight": 1.282051282051282, 
            "families": 1.0, 
            "id": "glove"
        }, 
        {
            "key": "4.331", 
            "swadesh100": 0.0, 
            "frequency": 247.0, 
            "languages": 1.0, 
            "out_edge": [], 
            "label": "palm of hand", 
            "concept": "palm of hand", 
            "weight": 1.0, 
            "body_part": 1.0, 
            "community": 38, 
            "normalized_weight": 0.9900990099009901, 
            "families": 1.0, 
            "id": "palm of hand"
        }, 
        {
            "key": "8.74", 
            "swadesh100": 0.0, 
            "frequency": 182.0, 
            "languages": 1.0, 
            "out_edge": [], 
            "label": "forked branch", 
            "concept": "forked branch", 
            "weight": 1.0, 
            "body_part": 0.0, 
            "community": 38, 
            "normalized_weight": 0.9174311926605505, 
            "families": 1.0, 
            "id": "forked branch"
        }
    ], 
    "graph": []
}