{
    "nodes": [
        {
            "key": "18.37", 
            "body_part": 0, 
            "community": 86, 
            "id": "refuse", 
            "out_edge": [], 
            "swadesh100": 0
        }, 
        {
            "key": "19.59", 
            "body_part": 0, 
            "community": 86, 
            "id": "hinder, prevent", 
            "out_edge": [
                [
                    "cluster_49_preserve, look after", 
                    "defend", 
                    5.0, 
                    217.39130434782606
                ]
            ], 
            "swadesh100": 0
        }, 
        {
            "key": "18.38", 
            "body_part": 0, 
            "community": 86, 
            "id": "forbid", 
            "out_edge": [
                [
                    "cluster_49_preserve, look after", 
                    "defend", 
                    5.0, 
                    217.39130434782606
                ]
            ], 
            "swadesh100": 0
        }, 
        {
            "key": "18.34", 
            "body_part": 0, 
            "community": 86, 
            "id": "deny", 
            "out_edge": [
                [
                    "cluster_252_no, negative", 
                    "no, negative", 
                    4.0, 
                    120.75471698113208
                ]
            ], 
            "swadesh100": 0
        }
    ], 
    "multigraph": false, 
    "graph": [], 
    "adjacency": [
        [
            {
                "weight": 80.0, 
                "languages": 3.0, 
                "families": 3.0, 
                "id": "hinder, prevent"
            }, 
            {
                "weight": 963.855421686747, 
                "languages": 10.0, 
                "families": 10.0, 
                "id": "forbid"
            }, 
            {
                "weight": 2036.3636363636363, 
                "languages": 26.0, 
                "families": 14.0, 
                "id": "deny"
            }
        ], 
        [
            {
                "weight": 80.0, 
                "languages": 3.0, 
                "families": 3.0, 
                "id": "refuse"
            }, 
            {
                "weight": 1339.5348837209303, 
                "languages": 14.0, 
                "families": 12.0, 
                "id": "forbid"
            }, 
            {
                "weight": 8.421052631578947, 
                "languages": 1.0, 
                "families": 1.0, 
                "id": "deny"
            }
        ], 
        [
            {
                "weight": 963.855421686747, 
                "languages": 10.0, 
                "families": 10.0, 
                "id": "refuse"
            }, 
            {
                "weight": 1339.5348837209303, 
                "languages": 14.0, 
                "families": 12.0, 
                "id": "hinder, prevent"
            }, 
            {
                "weight": 219.7802197802198, 
                "languages": 7.0, 
                "families": 5.0, 
                "id": "deny"
            }
        ], 
        [
            {
                "weight": 2036.3636363636363, 
                "languages": 26.0, 
                "families": 14.0, 
                "id": "refuse"
            }, 
            {
                "weight": 8.421052631578947, 
                "languages": 1.0, 
                "families": 1.0, 
                "id": "hinder, prevent"
            }, 
            {
                "weight": 219.7802197802198, 
                "languages": 7.0, 
                "families": 5.0, 
                "id": "forbid"
            }
        ]
    ], 
    "directed": false
}