{"nodes": [{"community": 48, "id": "fragrant, good smelling", "key": "15.25", "out_edge": [["cluster_60_bitter", "sweet", 5.0, 21.73913043478261]], "swadesh100": 0, "body_part": 0}, {"community": 48, "id": "rotten", "key": "5.125", "out_edge": [], "swadesh100": 0, "body_part": 0}, {"community": 48, "id": "sniff", "key": "15.212", "out_edge": [], "swadesh100": 0, "body_part": 0}, {"community": 48, "id": "smell (vb trans)", "key": "15.22", "out_edge": [["cluster_11_know", "feel", 8.0, 62.745098039215684], ["cluster_11_know", "hear", 5.0, 21.73913043478261]], "swadesh100": 0, "body_part": 0}, {"community": 48, "id": "smell (vb intrans)", "key": "15.21", "out_edge": [["cluster_11_know", "feel", 4.0, 14.545454545454545]], "swadesh100": 0, "body_part": 0}, {"community": 48, "id": "pus", "key": "4.857", "out_edge": [], "swadesh100": 0, "body_part": 0}, {"community": 48, "id": "stinking, bad smelling", "key": "15.26", "out_edge": [], "swadesh100": 0, "body_part": 0}], "graph": [], "directed": false, "adjacency": [[{"edge_width": 1.5, "id": "smell (vb trans)", "languages": 1.0, "families": 1.0, "weight": 0.9009009009009009}, {"edge_width": 1.5, "id": "sniff", "languages": 1.0, "families": 1.0, "weight": 0.9433962264150944}, {"edge_width": 1.6693548387096775, "id": "smell (vb intrans)", "languages": 6.0, "families": 6.0, "weight": 32.72727272727273}, {"edge_width": 1.5, "id": "stinking, bad smelling", "languages": 4.0, "families": 4.0, "weight": 14.285714285714285}], [{"edge_width": 1.5, "id": "smell (vb intrans)", "languages": 2.0, "families": 2.0, "weight": 3.3057851239669422}, {"edge_width": 1.6693548387096775, "id": "pus", "languages": 8.0, "families": 5.0, "weight": 21.929824561403507}, {"edge_width": 2.1774193548387095, "id": "stinking, bad smelling", "languages": 14.0, "families": 10.0, "weight": 88.49557522123894}], [{"edge_width": 1.5, "id": "fragrant, good smelling", "languages": 1.0, "families": 1.0, "weight": 0.9433962264150944}, {"edge_width": 5.7338709677419351, "id": "smell (vb trans)", "languages": 63.0, "families": 21.0, "weight": 512.7906976744187}, {"edge_width": 2.1774193548387095, "id": "smell (vb intrans)", "languages": 13.0, "families": 10.0, "weight": 99.00990099009901}], [{"edge_width": 1.5, "id": "fragrant, good smelling", "languages": 1.0, "families": 1.0, "weight": 0.9009009009009009}, {"edge_width": 5.7338709677419351, "id": "sniff", "languages": 63.0, "families": 21.0, "weight": 512.7906976744187}, {"edge_width": 2.854838709677419, "id": "smell (vb intrans)", "languages": 28.0, "families": 13.0, "weight": 164.07766990291262}, {"edge_width": 1.5, "id": "stinking, bad smelling", "languages": 1.0, "families": 1.0, "weight": 0.8695652173913043}], [{"edge_width": 1.6693548387096775, "id": "fragrant, good smelling", "languages": 6.0, "families": 6.0, "weight": 32.72727272727273}, {"edge_width": 2.854838709677419, "id": "smell (vb trans)", "languages": 28.0, "families": 13.0, "weight": 164.07766990291262}, {"edge_width": 1.5, "id": "rotten", "languages": 2.0, "families": 2.0, "weight": 3.3057851239669422}, {"edge_width": 2.1774193548387095, "id": "sniff", "languages": 13.0, "families": 10.0, "weight": 99.00990099009901}, {"edge_width": 1.8387096774193548, "id": "stinking, bad smelling", "languages": 7.0, "families": 7.0, "weight": 43.36283185840708}], [{"edge_width": 1.6693548387096775, "id": "rotten", "languages": 8.0, "families": 5.0, "weight": 21.929824561403507}, {"edge_width": 1.5, "id": "stinking, bad smelling", "languages": 2.0, "families": 2.0, "weight": 3.508771929824561}], [{"edge_width": 1.5, "id": "fragrant, good smelling", "languages": 4.0, "families": 4.0, "weight": 14.285714285714285}, {"edge_width": 1.5, "id": "smell (vb trans)", "languages": 1.0, "families": 1.0, "weight": 0.8695652173913043}, {"edge_width": 2.1774193548387095, "id": "rotten", "languages": 14.0, "families": 10.0, "weight": 88.49557522123894}, {"edge_width": 1.8387096774193548, "id": "smell (vb intrans)", "languages": 7.0, "families": 7.0, "weight": 43.36283185840708}, {"edge_width": 1.5, "id": "pus", "languages": 2.0, "families": 2.0, "weight": 3.508771929824561}]], "multigraph": false}