{"graph": [], "nodes": [{"swadesh100": 0, "out_edge": [["cluster_67_body", "body", 7.0, 44.14414414414414, "body"]], "body_part": 0, "key": "4.77", "community": 201, "id": "corpse"}, {"swadesh100": 1, "out_edge": [["cluster_178_disappear", "disappear", 4.0, 14.15929203539823, "disappear"], ["cluster_110_extinguish", "kill", 4.0, 13.008130081300814, "extinguish"]], "body_part": 0, "key": "4.75", "community": 201, "id": "die, dead"}], "adjacency": [[{"languages": 15.0, "edge_width": 3.5663265306122449, "weight": 156.4814814814815, "families": 13.0, "id": "die, dead"}], [{"languages": 15.0, "edge_width": 3.5663265306122449, "weight": 156.4814814814815, "families": 13.0, "id": "corpse"}, {"languages": 1.0, "edge_width": 1.5, "weight": 0.8, "families": 1.0, "id": "die, dead"}]], "multigraph": false, "directed": false}